MANIFEST.in
README.rst
setup.py
django_site_status.egg-info/PKG-INFO
django_site_status.egg-info/SOURCES.txt
django_site_status.egg-info/dependency_links.txt
django_site_status.egg-info/top_level.txt
site_status/__init__.py
site_status/admin.py
site_status/api.py
site_status/context_processors.py
site_status/models.py
site_status/migrations/0001_initial.py
site_status/migrations/0001_initial.pyc
site_status/migrations/__init__.py
site_status/migrations/__init__.pyc
site_status/tests/__init__.py