Metadata-Version: 1.1
Name: django-site-status
Version: 0.1.3
Summary: A simple Django app to issue site wide alerts
Home-page: https://github.com/changecoin/django-site-status
Author: Mantas Vidutis
Author-email: mantas@turbines.io
License: BSD License
Platform: UNKNOWN
Classifier: Environment :: Web Environment
Classifier: Framework :: Django
Classifier: Intended Audience :: Developers
Classifier: License :: OSI Approved :: BSD License
Classifier: Operating System :: OS Independent
Classifier: Programming Language :: Python
Classifier: Programming Language :: Python :: 2
Classifier: Programming Language :: Python :: 2.7
Classifier: Topic :: Internet :: WWW/HTTP
Classifier: Topic :: Internet :: WWW/HTTP :: Dynamic Content
Requires: django
